srsdb/__init__.py
srsdb/ebisu_database.py
srsdb/fsrs_database.py
srsdb/py.typed
srsdb/srs_database.py
srsdb-0.13.0.dist-info/licenses/LICENSE
srsdb-0.13.0.dist-info/METADATA
srsdb-0.13.0.dist-info/WHEEL
srsdb-0.13.0.dist-info/top_level.txt
srsdb-0.13.0.dist-info/RECORD
