Metadata-Version: 2.4
Name: srsdb
Version: 0.13.0
Summary: SQLite database for tracking SRS learning state with FSRS and Ebisu algorithms
Author: jomof
License-Expression: MIT
Project-URL: Homepage, https://github.com/jomof/srsdb
Project-URL: Documentation, https://github.com/jomof/srsdb#readme
Project-URL: Repository, https://github.com/jomof/srsdb
Project-URL: Bug Reports, https://github.com/jomof/srsdb/issues
Keywords: srs,spaced-repetition,flashcards,learning,fsrs,ebisu,memory
Classifier: Development Status :: 4 - Beta
Classifier: Intended Audience :: Developers
Classifier: Intended Audience :: Education
Classifier: Topic :: Education
Classifier: Topic :: Scientific/Engineering :: Artificial Intelligence
Classifier: Programming Language :: Python :: 3
Classifier: Programming Language :: Python :: 3.8
Classifier: Programming Language :: Python :: 3.9
Classifier: Programming Language :: Python :: 3.10
Classifier: Programming Language :: Python :: 3.11
Classifier: Programming Language :: Python :: 3.12
Classifier: Operating System :: OS Independent
Requires-Python: >=3.8
License-File: LICENSE
Provides-Extra: ebisu
Requires-Dist: ebisu>=2.0.0; extra == "ebisu"
Provides-Extra: dev
Requires-Dist: pytest>=7.0.0; extra == "dev"
Requires-Dist: pytest-cov>=4.0.0; extra == "dev"
Requires-Dist: mypy>=1.0.0; extra == "dev"
Requires-Dist: ebisu>=2.0.0; extra == "dev"
Dynamic: license-file
